flake8_pytest_style/__init__.py
flake8_pytest_style/config.py
flake8_pytest_style/errors.py
flake8_pytest_style/plugin.py
flake8_pytest_style/py.typed
flake8_pytest_style/utils.py
flake8_pytest_style/visitors/__init__.py
flake8_pytest_style/visitors/assertion.py
flake8_pytest_style/visitors/fail.py
flake8_pytest_style/visitors/fixtures.py
flake8_pytest_style/visitors/imports.py
flake8_pytest_style/visitors/marks.py
flake8_pytest_style/visitors/parametrize.py
flake8_pytest_style/visitors/patch.py
flake8_pytest_style/visitors/raises.py
flake8_pytest_style/visitors/t_functions.py
flake8_pytest_style/visitors/try_except.py
flake8_pytest_style/visitors/warns.py
flake8_pytest_style-2.2.0.dist-info/METADATA
flake8_pytest_style-2.2.0.dist-info/WHEEL
flake8_pytest_style-2.2.0.dist-info/entry_points.txt
flake8_pytest_style-2.2.0.dist-info/licenses/LICENSE
flake8_pytest_style-2.2.0.dist-info/RECORD
