Metadata-Version: 2.4
Name: flake8-pytest-style
Version: 2.2.0
Summary: A flake8 plugin checking common style issues or inconsistencies with pytest-based tests.
License-Expression: MIT
License-File: LICENSE
Keywords: flake8,pytest
Author: Mikhail Burshteyn
Author-email: mdburshteyn@gmail.com
Requires-Python: >=3.10
Classifier: Development Status :: 5 - Production/Stable
Classifier: Environment :: Console
Classifier: Environment :: Plugins
Classifier: Framework :: Flake8
Classifier: Framework :: Pytest
Classifier: Intended Audience :: Developers
Classifier: Operating System :: OS Independent
Classifier: Programming Language :: Python :: 3
Classifier: Programming Language :: Python :: 3.10
Classifier: Programming Language :: Python :: 3.11
Classifier: Programming Language :: Python :: 3.12
Classifier: Programming Language :: Python :: 3.13
Classifier: Programming Language :: Python :: 3.14
Classifier: Topic :: Software Development :: Quality Assurance
Classifier: Topic :: Software Development :: Testing
Classifier: Topic :: Software Development :: Testing :: Unit
Requires-Dist: flake8-plugin-utils (>=1.3.2,<2.0.0)
Project-URL: Homepage, https://pypi.org/project/flake8-pytest-style
Project-URL: Repository, https://github.com/m-burst/flake8-pytest-style
